PyPantry/__init__.py
PyPantry/basket.py
PyPantry/main.py
PyPantry-0.1.0.dist-info/LICENSE
PyPantry-0.1.0.dist-info/METADATA
PyPantry-0.1.0.dist-info/WHEEL
PyPantry-0.1.0.dist-info/top_level.txt
PyPantry-0.1.0.dist-info/RECORD
